{
  "name": "Sylvia Wong",
  "age": 29,
  "address": {
    "street": "Rebpak Street",
    "city": "Guefusu",
    "state": "LA",
    "zip": "33581"
  },
  "contact": {
    "phone": "(947) 621-8850",
    "servicePhone": "800249639"
  },
  "birthday": "2004-05-31T01:40:40.331Z",
  "ip": "13.213.191.178",
  "foo": "bar",
  "profile": {
    "about": "Lit wuidafub kolot fefbikniw loku ronu ajinaate wib bawasulo vineh movipige zetfugno guleti. Ji oluvulu zuztu neka wa eduzinsa bijruz no netjupuwi natja uhuapere tebosog ziwhip cod azmitdus wetir niggof nij. Dup kat fisoni vopiwa sud divjojzah wik irdasgow jonudi fopfujdog gocgalmel et ri bikkeli doruj jinipade ujinod. Ki awototbuv iwicorcu lav luhne fofkij an eleplim ma jorehdi epiped be. Uzu dir da fe pate raeda en nabni hoh ti uronez esdi warilenil ivbaoj zemnupnuj vebodpa. Sovol ampaf saf wahu liosusu zouz zekufas cus meojo tegric batu polehe wo puhtutwe ari. Nuug zoz um mibof rupu otkopse are fe li ili ej nelojda hohut raifi tinhuhna cezuk wukgappi.",
    "bio": "Bi ica tamkapi unso vowej caku ulisis sur esi robrijke heuj havef biduvulev cableri. Hasor odita me nomi hac hi fiku ba orgaima cem fofboce foluraidi ahuhig mu ejeposlok. Defo din zomwefduj jerozev co mattonze af ho fuwel huravu ole paj tiviij. Osururos to ihutejwep ufcewu itoin sek mijgelgav nol kurepnu hih guf ofe dinka. Humsa kimeno emejavhir oco vi mumlaj jifnav jivinu joedeasu pehnafce jim podo ket rar wusmuto nufier."
  },
  "apiKey": "1380332464ff63b4cffabfca2f8e3b173829cdb60af5106dd0ebb36217504cd5",
  "currency": {
    "code": "AFN",
    "name": "Afghanistan Afghani"
  }
}